README.rst
setup.py
DobotRPC/NetworkError.py
DobotRPC/RPCClient.py
DobotRPC/RPCClientAdapter.py
DobotRPC/RPCServer.py
DobotRPC/RPCServerAdapter.py
DobotRPC/__init__.py
DobotRPC.egg-info/PKG-INFO
DobotRPC.egg-info/SOURCES.txt
DobotRPC.egg-info/dependency_links.txt
DobotRPC.egg-info/requires.txt
DobotRPC.egg-info/top_level.txt
DobotRPC/Message/MessageCenter.py
DobotRPC/Message/MessageCenterError.py
DobotRPC/Message/__init__.py
DobotRPC/Utils/Loggers.py
DobotRPC/Utils/__init__.py