Metadata-Version: 2.1
Name: DobotRPC
Version: 4.8.7
Summary: Dobotlink communication module
Home-page: UNKNOWN
Author: songlijun
Author-email: songlijun@dobot.cc
License: Apache Licence
Keywords: websocket,JSON-RPC,asyncio,Dobot,Dobotlink,Client,Server
Platform: any
